{
  "meta": {
    "report_date": "11-Feb"
  },
  "stock": {
    "172": {
      "code": "10011004",
      "material": "MISC CLEAN UP SCRAP",
      "pile": "172",
      "operating_inventory_lbs": -9760,
      "month_begin_lbs": -9760,
      "receipts_lbs": 0,
      "issues_lbs": 0,
      "transfers_lbs": 0,
      "adjustments_lbs": 0,
      "depletions_lbs": 0,
      "last_zero_date": "10/21/2025"
    },
    "175": {
      "code": "10011004",
      "material": "MISC CLEAN UP SCRAP",
      "pile": "175",
      "operating_inventory_lbs": 2937490,
      "month_begin_lbs": 3097700,
      "receipts_lbs": 99240,
      "issues_lbs": 0,
      "transfers_lbs": 0,
      "adjustments_lbs": 0,
      "depletions_lbs": 0,
      "last_zero_date": "3/14/2023"
    },
    "17B": {
      "code": "10011004",
      "material": "MISC CLEAN UP SCRAP",
      "pile": "17B",
      "operating_inventory_lbs": 678800,
      "month_begin_lbs": 678800,
      "receipts_lbs": 0,
      "issues_lbs": 0,
      "transfers_lbs": 0,
      "adjustments_lbs": 0,
      "depletions_lbs": 0,
      "last_zero_date": "2/24/2025"
    },
    "17F": {
      "code": "10011004",
      "material": "MISC CLEAN UP SCRAP",
      "pile": "17F",
      "operating_inventory_lbs": 7801,
      "month_begin_lbs": 7801,
      "receipts_lbs": 0,
      "issues_lbs": 0,
      "transfers_lbs": 0,
      "adjustments_lbs": 0,
      "depletions_lbs": 0,
      "last_zero_date": "12/22/2025"
    },
    "17G": {
      "code": "10011004",
      "material": "MISC CLEAN UP SCRAP",
      "pile": "17G",
      "operating_inventory_lbs": 4751,
      "month_begin_lbs": 4751,
      "receipts_lbs": 0,
      "issues_lbs": 0,
      "transfers_lbs": 0,
      "adjustments_lbs": 0,
      "depletions_lbs": 0,
      "last_zero_date": "12/12/2025"
    },
    "17K": {
      "code": "10011004",
      "material": "MISC CLEAN UP SCRAP",
      "pile": "17K",
      "operating_inventory_lbs": 10601,
      "month_begin_lbs": 10601,
      "receipts_lbs": 0,
      "issues_lbs": 0,
      "transfers_lbs": 0,
      "adjustments_lbs": 0,
      "depletions_lbs": 0,
      "last_zero_date": "12/22/2025"
    },
    "17R": {
      "code": "10011004",
      "material": "MISC CLEAN UP SCRAP",
      "pile": "17R",
      "operating_inventory_lbs": 115051,
      "month_begin_lbs": 115051,
      "receipts_lbs": 0,
      "issues_lbs": 0,
      "transfers_lbs": 0,
      "adjustments_lbs": 0,
      "depletions_lbs": 0,
      "last_zero_date": "12/30/2025"
    },
    "17S": {
      "code": "10011004",
      "material": "MISC CLEAN UP SCRAP",
      "pile": "17S",
      "operating_inventory_lbs": 293950,
      "month_begin_lbs": 293950,
      "receipts_lbs": 0,
      "issues_lbs": 0,
      "transfers_lbs": 0,
      "adjustments_lbs": 0,
      "depletions_lbs": 0,
      "last_zero_date": "7/22/2021"
    },
    "17V": {
      "code": "10011004",
      "material": "MISC CLEAN UP SCRAP",
      "pile": "17V",
      "operating_inventory_lbs": 31360,
      "month_begin_lbs": 31360,
      "receipts_lbs": 0,
      "issues_lbs": 0,
      "transfers_lbs": 0,
      "adjustments_lbs": 0,
      "depletions_lbs": 0,
      "last_zero_date": "10/23/2025"
    },
    "17W": {
      "code": "10011004",
      "material": "MISC CLEAN UP SCRAP",
      "pile": "17W",
      "operating_inventory_lbs": 4940,
      "month_begin_lbs": 4940,
      "receipts_lbs": 0,
      "issues_lbs": 0,
      "transfers_lbs": 0,
      "adjustments_lbs": 0,
      "depletions_lbs": 0,
      "last_zero_date": "10/21/2024"
    },
    "17X": {
      "code": "10011004",
      "material": "MISC CLEAN UP SCRAP",
      "pile": "17X",
      "operating_inventory_lbs": 276719,
      "month_begin_lbs": 276719,
      "receipts_lbs": 0,
      "issues_lbs": 0,
      "transfers_lbs": 0,
      "adjustments_lbs": 0,
      "depletions_lbs": 0,
      "last_zero_date": "7/12/2018"
    },
    "17Z": {
      "code": "10011004",
      "material": "MISC CLEAN UP SCRAP",
      "pile": "17Z",
      "operating_inventory_lbs": 76198,
      "month_begin_lbs": 76198,
      "receipts_lbs": 0,
      "issues_lbs": 0,
      "transfers_lbs": 0,
      "adjustments_lbs": 0,
      "depletions_lbs": 0,
      "last_zero_date": "1/29/2018"
    },
    "281": {
      "code": "10011414",
      "material": "FRAGMENTED SCRAP",
      "pile": "281",
      "operating_inventory_lbs": 4589679,
      "month_begin_lbs": 3184889,
      "receipts_lbs": 2782440,
      "issues_lbs": 0,
      "transfers_lbs": 0,
      "adjustments_lbs": 0,
      "depletions_lbs": 0,
      "last_zero_date": "8/25/2025"
    },
    "282": {
      "code": "10011414",
      "material": "FRAGMENTED SCRAP",
      "pile": "282",
      "operating_inventory_lbs": 444160,
      "month_begin_lbs": 0,
      "receipts_lbs": 444160,
      "issues_lbs": 0,
      "transfers_lbs": 0,
      "adjustments_lbs": 0,
      "depletions_lbs": 0,
      "last_zero_date": "2/10/2026"
    },
    "283": {
      "code": "10011414",
      "material": "FRAGMENTED SCRAP",
      "pile": "283",
      "operating_inventory_lbs": 8623640,
      "month_begin_lbs": 7659940,
      "receipts_lbs": 2140650,
      "issues_lbs": 0,
      "transfers_lbs": 0,
      "adjustments_lbs": 0,
      "depletions_lbs": 0,
      "last_zero_date": "12/3/2025"
    },
    "166": {
      "code": "10011418",
      "material": "# 1 BUSHELINGS",
      "pile": "166",
      "operating_inventory_lbs": 656251,
      "month_begin_lbs": 656251,
      "receipts_lbs": 0,
      "issues_lbs": 0,
      "transfers_lbs": 0,
      "adjustments_lbs": 0,
      "depletions_lbs": 0,
      "last_zero_date": "11/20/2025"
    },
    "20H": {
      "code": "10011425",
      "material": "MIDDLETOWN SCRAP",
      "pile": "20H",
      "operating_inventory_lbs": 343860,
      "month_begin_lbs": 425350,
      "receipts_lbs": 310260,
      "issues_lbs": 0,
      "transfers_lbs": 0,
      "adjustments_lbs": 0,
      "depletions_lbs": 0,
      "last_zero_date": "12/11/2025"
    },
    "20X": {
      "code": "10011425",
      "material": "MIDDLETOWN SCRAP",
      "pile": "20X",
      "operating_inventory_lbs": 74801,
      "month_begin_lbs": 74801,
      "receipts_lbs": 0,
      "issues_lbs": 0,
      "transfers_lbs": 0,
      "adjustments_lbs": 0,
      "depletions_lbs": 0,
      "last_zero_date": "11/22/2021"
    },
    "ASN": {
      "code": "10011660",
      "material": "430/439/409 BLEND SC",
      "pile": "ASN",
      "operating_inventory_lbs": 0,
      "month_begin_lbs": 0,
      "receipts_lbs": 0,
      "issues_lbs": 0,
      "transfers_lbs": 0,
      "adjustments_lbs": 0,
      "depletions_lbs": 0,
      "last_zero_date": ""
    },
    "097": {
      "code": "10011446",
      "material": "HBI\\Hot Briq Iron",
      "pile": "097",
      "operating_inventory_lbs": 13227680,
      "month_begin_lbs": 12798860,
      "receipts_lbs": 3178170,
      "issues_lbs": 0,
      "transfers_lbs": 0,
      "adjustments_lbs": 0,
      "depletions_lbs": 0,
      "last_zero_date": "5/27/2025"
    },
    "098": {
      "code": "10011446",
      "material": "HBI\\Hot Briq Iron",
      "pile": "098",
      "operating_inventory_lbs": 6745040,
      "month_begin_lbs": 6701470,
      "receipts_lbs": 2455220,
      "issues_lbs": 0,
      "transfers_lbs": 0,
      "adjustments_lbs": 0,
      "depletions_lbs": 0,
      "last_zero_date": "10/10/2025"
    },
    "099": {
      "code": "10011446",
      "material": "HBI\\Hot Briq Iron",
      "pile": "099",
      "operating_inventory_lbs": 3864570,
      "month_begin_lbs": 3463020,
      "receipts_lbs": 3847600,
      "issues_lbs": 0,
      "transfers_lbs": 0,
      "adjustments_lbs": 0,
      "depletions_lbs": 0,
      "last_zero_date": "8/25/2025"
    },
    "401": {
      "code": "10011503",
      "material": "409 SCRAP",
      "pile": "401",
      "operating_inventory_lbs": 1389535,
      "month_begin_lbs": 1826685,
      "receipts_lbs": 535800,
      "issues_lbs": 0,
      "transfers_lbs": 542450,
      "adjustments_lbs": 0,
      "depletions_lbs": 0,
      "last_zero_date": "8/29/2025"
    },
    "408": {
      "code": "10011503",
      "material": "409 SCRAP",
      "pile": "408",
      "operating_inventory_lbs": 1659229,
      "month_begin_lbs": 2984179,
      "receipts_lbs": 0,
      "issues_lbs": 0,
      "transfers_lbs": -506450,
      "adjustments_lbs": 0,
      "depletions_lbs": 0,
      "last_zero_date": "1/30/2025"
    },
    "40C": {
      "code": "10011503",
      "material": "409 SCRAP",
      "pile": "40C",
      "operating_inventory_lbs": -46150,
      "month_begin_lbs": -10150,
      "receipts_lbs": 0,
      "issues_lbs": 0,
      "transfers_lbs": -36000,
      "adjustments_lbs": 0,
      "depletions_lbs": 0,
      "last_zero_date": "11/24/2025"
    },
    "40S": {
      "code": "10011503",
      "material": "409 SCRAP",
      "pile": "40S",
      "operating_inventory_lbs": 44840,
      "month_begin_lbs": 0,
      "receipts_lbs": 44840,
      "issues_lbs": 0,
      "transfers_lbs": 0,
      "adjustments_lbs": 0,
      "depletions_lbs": 0,
      "last_zero_date": "2/4/2026"
    },
    "504": {
      "code": "10011509",
      "material": "430 SCRAP",
      "pile": "504",
      "operating_inventory_lbs": 3826440,
      "month_begin_lbs": 4054810,
      "receipts_lbs": 591130,
      "issues_lbs": 0,
      "transfers_lbs": 0,
      "adjustments_lbs": 0,
      "depletions_lbs": 0,
      "last_zero_date": "7/9/2025"
    },
    "505": {
      "code": "10011509",
      "material": "430 SCRAP",
      "pile": "505",
      "operating_inventory_lbs": 2747800,
      "month_begin_lbs": 2865690,
      "receipts_lbs": 118460,
      "issues_lbs": 0,
      "transfers_lbs": 27550,
      "adjustments_lbs": 0,
      "depletions_lbs": 0,
      "last_zero_date": "9/22/2025"
    },
    "50C": {
      "code": "10011509",
      "material": "430 SCRAP",
      "pile": "50C",
      "operating_inventory_lbs": 170264,
      "month_begin_lbs": 197814,
      "receipts_lbs": 0,
      "issues_lbs": 0,
      "transfers_lbs": -27550,
      "adjustments_lbs": 0,
      "depletions_lbs": 0,
      "last_zero_date": "4/4/2025"
    },
    "418": {
      "code": "10011512",
      "material": "409 RECLAIM",
      "pile": "418",
      "operating_inventory_lbs": 502880,
      "month_begin_lbs": 494900,
      "receipts_lbs": 221080,
      "issues_lbs": 0,
      "transfers_lbs": 0,
      "adjustments_lbs": 0,
      "depletions_lbs": 0,
      "last_zero_date": "12/23/2025"
    },
    "41B": {
      "code": "10011512",
      "material": "409 RECLAIM",
      "pile": "41B",
      "operating_inventory_lbs": 41780,
      "month_begin_lbs": 135220,
      "receipts_lbs": 153300,
      "issues_lbs": 0,
      "transfers_lbs": 0,
      "adjustments_lbs": 0,
      "depletions_lbs": -76990,
      "last_zero_date": "2/10/2026"
    },
    "41X": {
      "code": "10011512",
      "material": "409 RECLAIM",
      "pile": "41X",
      "operating_inventory_lbs": 1297170,
      "month_begin_lbs": 1444730,
      "receipts_lbs": 50220,
      "issues_lbs": 0,
      "transfers_lbs": 0,
      "adjustments_lbs": 0,
      "depletions_lbs": 0,
      "last_zero_date": "8/29/2023"
    },
    "433": {
      "code": "10011513",
      "material": "409 CONVERTOR SCRAP",
      "pile": "433",
      "operating_inventory_lbs": 2016810,
      "month_begin_lbs": 2005990,
      "receipts_lbs": 395620,
      "issues_lbs": 0,
      "transfers_lbs": 0,
      "adjustments_lbs": 0,
      "depletions_lbs": 0,
      "last_zero_date": "3/24/2025"
    },
    "434": {
      "code": "10011513",
      "material": "409 CONVERTOR SCRAP",
      "pile": "434",
      "operating_inventory_lbs": 1788980,
      "month_begin_lbs": 1788980,
      "receipts_lbs": 0,
      "issues_lbs": 0,
      "transfers_lbs": 0,
      "adjustments_lbs": 0,
      "depletions_lbs": 0,
      "last_zero_date": "10/1/2025"
    },
    "132": {
      "code": "10011515",
      "material": "446-24 Scrap",
      "pile": "132",
      "operating_inventory_lbs": 85249,
      "month_begin_lbs": 85249,
      "receipts_lbs": 0,
      "issues_lbs": 0,
      "transfers_lbs": 0,
      "adjustments_lbs": 0,
      "depletions_lbs": 0,
      "last_zero_date": "5/18/2021"
    },
    "134": {
      "code": "10011515",
      "material": "446-24 Scrap",
      "pile": "134",
      "operating_inventory_lbs": 21751,
      "month_begin_lbs": 21751,
      "receipts_lbs": 0,
      "issues_lbs": 0,
      "transfers_lbs": 0,
      "adjustments_lbs": 0,
      "depletions_lbs": 0,
      "last_zero_date": "11/19/2025"
    },
    "13C": {
      "code": "10011515",
      "material": "446-24 Scrap",
      "pile": "13C",
      "operating_inventory_lbs": 3399,
      "month_begin_lbs": 3399,
      "receipts_lbs": 0,
      "issues_lbs": 0,
      "transfers_lbs": 0,
      "adjustments_lbs": 0,
      "depletions_lbs": 0,
      "last_zero_date": "4/30/2021"
    },
    "645": {
      "code": "10011516",
      "material": "409NI SCRAP",
      "pile": "645",
      "operating_inventory_lbs": 456980,
      "month_begin_lbs": 371260,
      "receipts_lbs": 85720,
      "issues_lbs": 0,
      "transfers_lbs": 0,
      "adjustments_lbs": 0,
      "depletions_lbs": 0,
      "last_zero_date": "7/8/2025"
    },
    "64C": {
      "code": "10011516",
      "material": "409NI SCRAP",
      "pile": "64C",
      "operating_inventory_lbs": 14420,
      "month_begin_lbs": 14420,
      "receipts_lbs": 0,
      "issues_lbs": 0,
      "transfers_lbs": 0,
      "adjustments_lbs": 0,
      "depletions_lbs": 0,
      "last_zero_date": "5/5/2025"
    },
    "247": {
      "code": "10011521",
      "material": "435 SCRAP",
      "pile": "247",
      "operating_inventory_lbs": 2646949,
      "month_begin_lbs": 3596500,
      "receipts_lbs": 0,
      "issues_lbs": 0,
      "transfers_lbs": -148650,
      "adjustments_lbs": -1,
      "depletions_lbs": 0,
      "last_zero_date": "5/20/2025"
    },
    "248": {
      "code": "10011521",
      "material": "435 SCRAP",
      "pile": "248",
      "operating_inventory_lbs": 167751,
      "month_begin_lbs": 0,
      "receipts_lbs": 0,
      "issues_lbs": 0,
      "transfers_lbs": 167750,
      "adjustments_lbs": 1,
      "depletions_lbs": 0,
      "last_zero_date": "2/11/2026"
    },
    "24C": {
      "code": "10011521",
      "material": "435 SCRAP",
      "pile": "24C",
      "operating_inventory_lbs": 317700,
      "month_begin_lbs": 336800,
      "receipts_lbs": 0,
      "issues_lbs": 0,
      "transfers_lbs": -19100,
      "adjustments_lbs": 0,
      "depletions_lbs": 0,
      "last_zero_date": "12/18/2023"
    },
    "659": {
      "code": "10011526",
      "material": "409NI RECLAIM",
      "pile": "659",
      "operating_inventory_lbs": 118580,
      "month_begin_lbs": 118580,
      "receipts_lbs": 0,
      "issues_lbs": 0,
      "transfers_lbs": 0,
      "adjustments_lbs": 0,
      "depletions_lbs": 0,
      "last_zero_date": "11/18/2025"
    },
    "321": {
      "code": "10011528",
      "material": "409 HOME SCRAP",
      "pile": "321",
      "operating_inventory_lbs": 192160,
      "month_begin_lbs": 73920,
      "receipts_lbs": 103540,
      "issues_lbs": 0,
      "transfers_lbs": 45050,
      "adjustments_lbs": 0,
      "depletions_lbs": 0,
      "last_zero_date": "9/25/2025"
    },
    "32C": {
      "code": "10011528",
      "material": "409 HOME SCRAP",
      "pile": "32C",
      "operating_inventory_lbs": 178652,
      "month_begin_lbs": 178652,
      "receipts_lbs": 0,
      "issues_lbs": 0,
      "transfers_lbs": 0,
      "adjustments_lbs": 0,
      "depletions_lbs": 0,
      "last_zero_date": "5/17/2021"
    },
    "32L": {
      "code": "10011528",
      "material": "409 HOME SCRAP",
      "pile": "32L",
      "operating_inventory_lbs": 30750,
      "month_begin_lbs": 24240,
      "receipts_lbs": 51560,
      "issues_lbs": 0,
      "transfers_lbs": -45050,
      "adjustments_lbs": 0,
      "depletions_lbs": 0,
      "last_zero_date": "9/3/2025"
    },
    "32U": {
      "code": "10011528",
      "material": "409 HOME SCRAP",
      "pile": "32U",
      "operating_inventory_lbs": 83500,
      "month_begin_lbs": 83500,
      "receipts_lbs": 0,
      "issues_lbs": 0,
      "transfers_lbs": 0,
      "adjustments_lbs": 0,
      "depletions_lbs": 0,
      "last_zero_date": "9/17/2021"
    },
    "518": {
      "code": "10011529",
      "material": "430 & 440 HOME",
      "pile": "518",
      "operating_inventory_lbs": 144930,
      "month_begin_lbs": 121550,
      "receipts_lbs": 23380,
      "issues_lbs": 0,
      "transfers_lbs": 0,
      "adjustments_lbs": 0,
      "depletions_lbs": 0,
      "last_zero_date": "9/24/2024"
    },
    "51C": {
      "code": "10011529",
      "material": "430 & 440 HOME",
      "pile": "51C",
      "operating_inventory_lbs": 177920,
      "month_begin_lbs": 177920,
      "receipts_lbs": 0,
      "issues_lbs": 0,
      "transfers_lbs": 0,
      "adjustments_lbs": 0,
      "depletions_lbs": 0,
      "last_zero_date": "6/3/2021"
    },
    "51U": {
      "code": "10011529",
      "material": "430 & 440 HOME",
      "pile": "51U",
      "operating_inventory_lbs": 29840,
      "month_begin_lbs": 29840,
      "receipts_lbs": 0,
      "issues_lbs": 0,
      "transfers_lbs": 0,
      "adjustments_lbs": 0,
      "depletions_lbs": 0,
      "last_zero_date": "12/26/2025"
    },
    "951": {
      "code": "10011531",
      "material": "436 HOME SCRAP",
      "pile": "951",
      "operating_inventory_lbs": 7600,
      "month_begin_lbs": 0,
      "receipts_lbs": 0,
      "issues_lbs": 0,
      "transfers_lbs": 50700,
      "adjustments_lbs": 0,
      "depletions_lbs": 0,
      "last_zero_date": "2/10/2026"
    },
    "956": {
      "code": "10011531",
      "material": "436 HOME SCRAP",
      "pile": "956",
      "operating_inventory_lbs": 1,
      "month_begin_lbs": 0,
      "receipts_lbs": 0,
      "issues_lbs": 0,
      "transfers_lbs": 0,
      "adjustments_lbs": 1,
      "depletions_lbs": 0,
      "last_zero_date": "2/6/2026"
    },
    "957": {
      "code": "10011531",
      "material": "436 HOME SCRAP",
      "pile": "957",
      "operating_inventory_lbs": 215630,
      "month_begin_lbs": 215632,
      "receipts_lbs": 0,
      "issues_lbs": 0,
      "transfers_lbs": 0,
      "adjustments_lbs": -2,
      "depletions_lbs": 0,
      "last_zero_date": "5/30/2018"
    },
    "958": {
      "code": "10011531",
      "material": "436 HOME SCRAP",
      "pile": "958",
      "operating_inventory_lbs": 41110,
      "month_begin_lbs": 41110,
      "receipts_lbs": 0,
      "issues_lbs": 0,
      "transfers_lbs": 0,
      "adjustments_lbs": 0,
      "depletions_lbs": 0,
      "last_zero_date": "1/31/2024"
    },
    "95C": {
      "code": "10011531",
      "material": "436 HOME SCRAP",
      "pile": "95C",
      "operating_inventory_lbs": 17610,
      "month_begin_lbs": 17610,
      "receipts_lbs": 0,
      "issues_lbs": 0,
      "transfers_lbs": 0,
      "adjustments_lbs": 0,
      "depletions_lbs": 0,
      "last_zero_date": "9/15/2022"
    },
    "95H": {
      "code": "10011531",
      "material": "436 HOME SCRAP",
      "pile": "95H",
      "operating_inventory_lbs": 50,
      "month_begin_lbs": 16050,
      "receipts_lbs": 0,
      "issues_lbs": 0,
      "transfers_lbs": -16000,
      "adjustments_lbs": 0,
      "depletions_lbs": 0,
      "last_zero_date": "4/12/2023"
    },
    "95J": {
      "code": "10011531",
      "material": "436 HOME SCRAP",
      "pile": "95J",
      "operating_inventory_lbs": 16001,
      "month_begin_lbs": 0,
      "receipts_lbs": 0,
      "issues_lbs": 0,
      "transfers_lbs": 16000,
      "adjustments_lbs": 1,
      "depletions_lbs": 0,
      "last_zero_date": "2/6/2026"
    },
    "95U": {
      "code": "10011531",
      "material": "436 HOME SCRAP",
      "pile": "95U",
      "operating_inventory_lbs": -540,
      "month_begin_lbs": 0,
      "receipts_lbs": 50160,
      "issues_lbs": 0,
      "transfers_lbs": -50700,
      "adjustments_lbs": 0,
      "depletions_lbs": 0,
      "last_zero_date": "2/3/2026"
    },
    "620": {
      "code": "10011532",
      "material": "409NI HOME SCRAP",
      "pile": "620",
      "operating_inventory_lbs": 45900,
      "month_begin_lbs": 45900,
      "receipts_lbs": 0,
      "issues_lbs": 0,
      "transfers_lbs": 0,
      "adjustments_lbs": 0,
      "depletions_lbs": 0,
      "last_zero_date": "12/12/2025"
    },
    "62Q": {
      "code": "10011532",
      "material": "409NI HOME SCRAP",
      "pile": "62Q",
      "operating_inventory_lbs": 108700,
      "month_begin_lbs": 108700,
      "receipts_lbs": 0,
      "issues_lbs": 0,
      "transfers_lbs": 0,
      "adjustments_lbs": 0,
      "depletions_lbs": 0,
      "last_zero_date": "6/27/2018"
    },
    "62U": {
      "code": "10011532",
      "material": "409NI HOME SCRAP",
      "pile": "62U",
      "operating_inventory_lbs": 57460,
      "month_begin_lbs": 57460,
      "receipts_lbs": 0,
      "issues_lbs": 0,
      "transfers_lbs": 0,
      "adjustments_lbs": 0,
      "depletions_lbs": 0,
      "last_zero_date": "5/30/2017"
    },
    "62Z": {
      "code": "10011532",
      "material": "409NI HOME SCRAP",
      "pile": "62Z",
      "operating_inventory_lbs": 29900,
      "month_begin_lbs": 29900,
      "receipts_lbs": 0,
      "issues_lbs": 0,
      "transfers_lbs": 0,
      "adjustments_lbs": 0,
      "depletions_lbs": 0,
      "last_zero_date": "1/16/2026"
    },
    "154": {
      "code": "10011533",
      "material": "181/409 BLEND SCRAP",
      "pile": "154",
      "operating_inventory_lbs": 479079,
      "month_begin_lbs": 859679,
      "receipts_lbs": 0,
      "issues_lbs": 0,
      "transfers_lbs": 28050,
      "adjustments_lbs": 0,
      "depletions_lbs": 0,
      "last_zero_date": "4/9/2025"
    },
    "155": {
      "code": "10011533",
      "material": "181/409 BLEND SCRAP",
      "pile": "155",
      "operating_inventory_lbs": 3205570,
      "month_begin_lbs": 3233620,
      "receipts_lbs": 0,
      "issues_lbs": 0,
      "transfers_lbs": -28050,
      "adjustments_lbs": 0,
      "depletions_lbs": 0,
      "last_zero_date": "7/16/2025"
    },
    "156": {
      "code": "10011533",
      "material": "181/409 BLEND SCRAP",
      "pile": "156",
      "operating_inventory_lbs": 36300,
      "month_begin_lbs": 0,
      "receipts_lbs": 36300,
      "issues_lbs": 0,
      "transfers_lbs": 0,
      "adjustments_lbs": 0,
      "depletions_lbs": 0,
      "last_zero_date": "2/11/2026"
    },
    "15G": {
      "code": "10011533",
      "material": "181/409 BLEND SCRAP",
      "pile": "15G",
      "operating_inventory_lbs": 185350,
      "month_begin_lbs": 185350,
      "receipts_lbs": 0,
      "issues_lbs": 0,
      "transfers_lbs": 0,
      "adjustments_lbs": 0,
      "depletions_lbs": 0,
      "last_zero_date": "1/22/2026"
    },
    "15P": {
      "code": "10011533",
      "material": "181/409 BLEND SCRAP",
      "pile": "15P",
      "operating_inventory_lbs": 37980,
      "month_begin_lbs": 37980,
      "receipts_lbs": 0,
      "issues_lbs": 0,
      "transfers_lbs": 0,
      "adjustments_lbs": 0,
      "depletions_lbs": 0,
      "last_zero_date": "1/30/2026"
    },
    "15T": {
      "code": "10011533",
      "material": "181/409 BLEND SCRAP",
      "pile": "15T",
      "operating_inventory_lbs": 199990,
      "month_begin_lbs": 159050,
      "receipts_lbs": 40940,
      "issues_lbs": 0,
      "transfers_lbs": 0,
      "adjustments_lbs": 0,
      "depletions_lbs": 0,
      "last_zero_date": "1/27/2026"
    },
    "736": {
      "code": "10011536",
      "material": "300 STAINLESS SCRAP",
      "pile": "736",
      "operating_inventory_lbs": 1063271,
      "month_begin_lbs": 1083621,
      "receipts_lbs": 0,
      "issues_lbs": 0,
      "transfers_lbs": 0,
      "adjustments_lbs": 0,
      "depletions_lbs": 0,
      "last_zero_date": "7/9/2025"
    },
    "493": {
      "code": "10011540",
      "material": "430 TUNDISH SKULL",
      "pile": "493",
      "operating_inventory_lbs": 903610,
      "month_begin_lbs": 869190,
      "receipts_lbs": 34420,
      "issues_lbs": 0,
      "transfers_lbs": 0,
      "adjustments_lbs": 0,
      "depletions_lbs": 0,
      "last_zero_date": "8/30/2023"
    },
    "761": {
      "code": "10011542",
      "material": "444 RECLAIM",
      "pile": "761",
      "operating_inventory_lbs": 588170,
      "month_begin_lbs": 588170,
      "receipts_lbs": 0,
      "issues_lbs": 0,
      "transfers_lbs": 0,
      "adjustments_lbs": 0,
      "depletions_lbs": 0,
      "last_zero_date": "11/30/2021"
    },
    "915": {
      "code": "10011543",
      "material": "436 TUNDISH",
      "pile": "915",
      "operating_inventory_lbs": 284210,
      "month_begin_lbs": 198300,
      "receipts_lbs": 115960,
      "issues_lbs": 0,
      "transfers_lbs": 0,
      "adjustments_lbs": 0,
      "depletions_lbs": 0,
      "last_zero_date": "12/19/2025"
    },
    "254": {
      "code": "10011545",
      "material": "435 TUNDISH",
      "pile": "254",
      "operating_inventory_lbs": -82611,
      "month_begin_lbs": 52640,
      "receipts_lbs": 0,
      "issues_lbs": 0,
      "transfers_lbs": -77250,
      "adjustments_lbs": -1,
      "depletions_lbs": 0,
      "last_zero_date": "4/4/2024"
    },
    "255": {
      "code": "10011545",
      "material": "435 TUNDISH",
      "pile": "255",
      "operating_inventory_lbs": 125371,
      "month_begin_lbs": 0,
      "receipts_lbs": 48120,
      "issues_lbs": 0,
      "transfers_lbs": 77250,
      "adjustments_lbs": 1,
      "depletions_lbs": 0,
      "last_zero_date": "2/6/2026"
    },
    "770": {
      "code": "10011546",
      "material": "444 TUNDISH",
      "pile": "770",
      "operating_inventory_lbs": 25580,
      "month_begin_lbs": 25580,
      "receipts_lbs": 0,
      "issues_lbs": 0,
      "transfers_lbs": 0,
      "adjustments_lbs": 0,
      "depletions_lbs": 0,
      "last_zero_date": "1/16/2026"
    },
    "596": {
      "code": "10011557",
      "material": "181 HOME SCRAP",
      "pile": "596",
      "operating_inventory_lbs": 11040,
      "month_begin_lbs": 87040,
      "receipts_lbs": 0,
      "issues_lbs": 0,
      "transfers_lbs": 0,
      "adjustments_lbs": 0,
      "depletions_lbs": 0,
      "last_zero_date": "11/21/2025"
    },
    "59A": {
      "code": "10011557",
      "material": "181 HOME SCRAP",
      "pile": "59A",
      "operating_inventory_lbs": 19380,
      "month_begin_lbs": 19380,
      "receipts_lbs": 0,
      "issues_lbs": 0,
      "transfers_lbs": 0,
      "adjustments_lbs": 0,
      "depletions_lbs": 0,
      "last_zero_date": "3/28/2025"
    },
    "59C": {
      "code": "10011557",
      "material": "181 HOME SCRAP",
      "pile": "59C",
      "operating_inventory_lbs": 417680,
      "month_begin_lbs": 417680,
      "receipts_lbs": 0,
      "issues_lbs": 0,
      "transfers_lbs": 0,
      "adjustments_lbs": 0,
      "depletions_lbs": 0,
      "last_zero_date": "7/12/2021"
    },
    "59H": {
      "code": "10011557",
      "material": "181 HOME SCRAP",
      "pile": "59H",
      "operating_inventory_lbs": 64840,
      "month_begin_lbs": 94090,
      "receipts_lbs": 0,
      "issues_lbs": 0,
      "transfers_lbs": 0,
      "adjustments_lbs": 0,
      "depletions_lbs": 0,
      "last_zero_date": "2/13/2025"
    },
    "59R": {
      "code": "10011557",
      "material": "181 HOME SCRAP",
      "pile": "59R",
      "operating_inventory_lbs": 60901,
      "month_begin_lbs": 60901,
      "receipts_lbs": 0,
      "issues_lbs": 0,
      "transfers_lbs": 0,
      "adjustments_lbs": 0,
      "depletions_lbs": 0,
      "last_zero_date": "12/10/2025"
    },
    "59U": {
      "code": "10011557",
      "material": "181 HOME SCRAP",
      "pile": "59U",
      "operating_inventory_lbs": 27680,
      "month_begin_lbs": 0,
      "receipts_lbs": 27680,
      "issues_lbs": 0,
      "transfers_lbs": 0,
      "adjustments_lbs": 0,
      "depletions_lbs": 0,
      "last_zero_date": "2/10/2026"
    },
    "59X": {
      "code": "10011557",
      "material": "181 HOME SCRAP",
      "pile": "59X",
      "operating_inventory_lbs": 31301,
      "month_begin_lbs": 31301,
      "receipts_lbs": 0,
      "issues_lbs": 0,
      "transfers_lbs": 0,
      "adjustments_lbs": 0,
      "depletions_lbs": 0,
      "last_zero_date": "12/31/2025"
    },
    "606": {
      "code": "10011558",
      "material": "181 SCRAP",
      "pile": "606",
      "operating_inventory_lbs": 5782939,
      "month_begin_lbs": 6172289,
      "receipts_lbs": 0,
      "issues_lbs": 0,
      "transfers_lbs": 9350,
      "adjustments_lbs": 0,
      "depletions_lbs": 0,
      "last_zero_date": "11/5/2024"
    },
    "60C": {
      "code": "10011558",
      "material": "181 SCRAP",
      "pile": "60C",
      "operating_inventory_lbs": -380,
      "month_begin_lbs": 8970,
      "receipts_lbs": 0,
      "issues_lbs": 0,
      "transfers_lbs": -9350,
      "adjustments_lbs": 0,
      "depletions_lbs": 0,
      "last_zero_date": "1/21/2026"
    },
    "580": {
      "code": "10011559",
      "material": "181 TUNDISH",
      "pile": "580",
      "operating_inventory_lbs": 134280,
      "month_begin_lbs": 112060,
      "receipts_lbs": 22220,
      "issues_lbs": 0,
      "transfers_lbs": 0,
      "adjustments_lbs": 0,
      "depletions_lbs": 0,
      "last_zero_date": "1/15/2026"
    },
    "58A": {
      "code": "10011559",
      "material": "181 TUNDISH",
      "pile": "58A",
      "operating_inventory_lbs": 367970,
      "month_begin_lbs": 330530,
      "receipts_lbs": 37440,
      "issues_lbs": 0,
      "transfers_lbs": 0,
      "adjustments_lbs": 0,
      "depletions_lbs": 0,
      "last_zero_date": "9/12/2023"
    },
    "58R": {
      "code": "10011559",
      "material": "181 TUNDISH",
      "pile": "58R",
      "operating_inventory_lbs": 54601,
      "month_begin_lbs": 54601,
      "receipts_lbs": 0,
      "issues_lbs": 0,
      "transfers_lbs": 0,
      "adjustments_lbs": 0,
      "depletions_lbs": 0,
      "last_zero_date": "12/10/2025"
    },
    "58Z": {
      "code": "10011559",
      "material": "181 TUNDISH",
      "pile": "58Z",
      "operating_inventory_lbs": 103990,
      "month_begin_lbs": 103990,
      "receipts_lbs": 0,
      "issues_lbs": 0,
      "transfers_lbs": 0,
      "adjustments_lbs": 0,
      "depletions_lbs": 0,
      "last_zero_date": "2/17/2020"
    },
    "816": {
      "code": "10011560",
      "material": "151 HOME",
      "pile": "816",
      "operating_inventory_lbs": 49290,
      "month_begin_lbs": 25480,
      "receipts_lbs": 29360,
      "issues_lbs": 0,
      "transfers_lbs": 0,
      "adjustments_lbs": 0,
      "depletions_lbs": 0,
      "last_zero_date": "6/19/2025"
    },
    "81C": {
      "code": "10011560",
      "material": "151 HOME",
      "pile": "81C",
      "operating_inventory_lbs": 137510,
      "month_begin_lbs": 137510,
      "receipts_lbs": 0,
      "issues_lbs": 0,
      "transfers_lbs": 0,
      "adjustments_lbs": 0,
      "depletions_lbs": 0,
      "last_zero_date": "5/13/2022"
    },
    "823": {
      "code": "10011561",
      "material": "151 RECLAIM",
      "pile": "823",
      "operating_inventory_lbs": 317590,
      "month_begin_lbs": 347840,
      "receipts_lbs": 0,
      "issues_lbs": 0,
      "transfers_lbs": 0,
      "adjustments_lbs": 0,
      "depletions_lbs": 0,
      "last_zero_date": "4/26/2024"
    },
    "82B": {
      "code": "10011561",
      "material": "151 RECLAIM",
      "pile": "82B",
      "operating_inventory_lbs": 166911,
      "month_begin_lbs": 197061,
      "receipts_lbs": 0,
      "issues_lbs": 0,
      "transfers_lbs": 0,
      "adjustments_lbs": 0,
      "depletions_lbs": 0,
      "last_zero_date": "1/17/2024"
    },
    "833": {
      "code": "10011562",
      "material": "151 TUNDISH",
      "pile": "833",
      "operating_inventory_lbs": 638570,
      "month_begin_lbs": 610190,
      "receipts_lbs": 48180,
      "issues_lbs": 0,
      "transfers_lbs": 0,
      "adjustments_lbs": 0,
      "depletions_lbs": 0,
      "last_zero_date": "6/15/2023"
    },
    "313": {
      "code": "10011647",
      "material": "409 TUNDISH",
      "pile": "313",
      "operating_inventory_lbs": 171730,
      "month_begin_lbs": 255440,
      "receipts_lbs": 158940,
      "issues_lbs": 0,
      "transfers_lbs": 0,
      "adjustments_lbs": 0,
      "depletions_lbs": 0,
      "last_zero_date": "1/15/2026"
    },
    "674": {
      "code": "10011650",
      "material": "409NI TUNDISH",
      "pile": "674",
      "operating_inventory_lbs": 95320,
      "month_begin_lbs": 95320,
      "receipts_lbs": 0,
      "issues_lbs": 0,
      "transfers_lbs": 0,
      "adjustments_lbs": 0,
      "depletions_lbs": 0,
      "last_zero_date": "10/16/2025"
    },
    "484": {
      "code": "10011651",
      "material": "430 RECLAIM",
      "pile": "484",
      "operating_inventory_lbs": 131110,
      "month_begin_lbs": 131110,
      "receipts_lbs": 0,
      "issues_lbs": 0,
      "transfers_lbs": 0,
      "adjustments_lbs": 0,
      "depletions_lbs": 0,
      "last_zero_date": "11/10/2025"
    },
    "901": {
      "code": "10011652",
      "material": "436 RECLAIM",
      "pile": "901",
      "operating_inventory_lbs": 111670,
      "month_begin_lbs": 0,
      "receipts_lbs": 203020,
      "issues_lbs": 0,
      "transfers_lbs": 0,
      "adjustments_lbs": 0,
      "depletions_lbs": 0,
      "last_zero_date": "2/3/2026"
    },
    "234": {
      "code": "10011653",
      "material": "435 RECLAIM",
      "pile": "234",
      "operating_inventory_lbs": 96780,
      "month_begin_lbs": 96780,
      "receipts_lbs": 0,
      "issues_lbs": 0,
      "transfers_lbs": 0,
      "adjustments_lbs": 0,
      "depletions_lbs": 0,
      "last_zero_date": "12/3/2025"
    },
    "612": {
      "code": "10011654",
      "material": "181 RECLAIM",
      "pile": "612",
      "operating_inventory_lbs": 113240,
      "month_begin_lbs": 188690,
      "receipts_lbs": 0,
      "issues_lbs": 0,
      "transfers_lbs": 0,
      "adjustments_lbs": 0,
      "depletions_lbs": 0,
      "last_zero_date": "10/7/2025"
    },
    "944": {
      "code": "10011657",
      "material": "436 SCRAP",
      "pile": "944",
      "operating_inventory_lbs": 2964690,
      "month_begin_lbs": 3044780,
      "receipts_lbs": 230510,
      "issues_lbs": 0,
      "transfers_lbs": 0,
      "adjustments_lbs": 0,
      "depletions_lbs": 0,
      "last_zero_date": "8/6/2025"
    },
    "94C": {
      "code": "10011657",
      "material": "436 SCRAP",
      "pile": "94C",
      "operating_inventory_lbs": 220170,
      "month_begin_lbs": 220170,
      "receipts_lbs": 0,
      "issues_lbs": 0,
      "transfers_lbs": 0,
      "adjustments_lbs": 0,
      "depletions_lbs": 0,
      "last_zero_date": "5/28/2025"
    },
    "144": {
      "code": "10011660",
      "material": "430/439/409 BLEND SC",
      "pile": "144",
      "operating_inventory_lbs": 4345180,
      "month_begin_lbs": 4540910,
      "receipts_lbs": 136020,
      "issues_lbs": 0,
      "transfers_lbs": -159000,
      "adjustments_lbs": 0,
      "depletions_lbs": 0,
      "last_zero_date": "11/26/2024"
    },
    "147": {
      "code": "10011660",
      "material": "430/439/409 BLEND SC",
      "pile": "147",
      "operating_inventory_lbs": 6484646,
      "month_begin_lbs": 6676416,
      "receipts_lbs": 1182780,
      "issues_lbs": 0,
      "transfers_lbs": 159000,
      "adjustments_lbs": 0,
      "depletions_lbs": 0,
      "last_zero_date": "8/28/2025"
    },
    "14A": {
      "code": "10011660",
      "material": "430/439/409 BLEND SC",
      "pile": "14A",
      "operating_inventory_lbs": 73640,
      "month_begin_lbs": 73640,
      "receipts_lbs": 0,
      "issues_lbs": 0,
      "transfers_lbs": 0,
      "adjustments_lbs": 0,
      "depletions_lbs": 0,
      "last_zero_date": "4/17/2025"
    },
    "260": {
      "code": "10011663",
      "material": "435 HOME SCRAP",
      "pile": "260",
      "operating_inventory_lbs": 6301,
      "month_begin_lbs": 24401,
      "receipts_lbs": 0,
      "issues_lbs": 0,
      "transfers_lbs": 0,
      "adjustments_lbs": 0,
      "depletions_lbs": 0,
      "last_zero_date": "9/18/2025"
    },
    "26C": {
      "code": "10011663",
      "material": "435 HOME SCRAP",
      "pile": "26C",
      "operating_inventory_lbs": 78779,
      "month_begin_lbs": 78779,
      "receipts_lbs": 0,
      "issues_lbs": 0,
      "transfers_lbs": 0,
      "adjustments_lbs": 0,
      "depletions_lbs": 0,
      "last_zero_date": "6/23/2023"
    },
    "26U": {
      "code": "10011663",
      "material": "435 HOME SCRAP",
      "pile": "26U",
      "operating_inventory_lbs": 5820,
      "month_begin_lbs": 0,
      "receipts_lbs": 5820,
      "issues_lbs": 0,
      "transfers_lbs": 0,
      "adjustments_lbs": 0,
      "depletions_lbs": 0,
      "last_zero_date": "2/10/2026"
    },
    "361": {
      "code": "10011667",
      "material": "439 RECLAIM",
      "pile": "361",
      "operating_inventory_lbs": 82530,
      "month_begin_lbs": 422140,
      "receipts_lbs": 38140,
      "issues_lbs": 0,
      "transfers_lbs": 0,
      "adjustments_lbs": 0,
      "depletions_lbs": 0,
      "last_zero_date": "9/8/2025"
    },
    "370": {
      "code": "10011668",
      "material": "439 TUNDISH",
      "pile": "370",
      "operating_inventory_lbs": 760210,
      "month_begin_lbs": 636330,
      "receipts_lbs": 123880,
      "issues_lbs": 0,
      "transfers_lbs": 0,
      "adjustments_lbs": 0,
      "depletions_lbs": 0,
      "last_zero_date": "5/29/2025"
    },
    "384": {
      "code": "10011669",
      "material": "439 HOME SCRAP",
      "pile": "384",
      "operating_inventory_lbs": 665831,
      "month_begin_lbs": 535791,
      "receipts_lbs": 29540,
      "issues_lbs": 0,
      "transfers_lbs": 100500,
      "adjustments_lbs": 0,
      "depletions_lbs": 0,
      "last_zero_date": "12/10/2025"
    },
    "38C": {
      "code": "10011669",
      "material": "439 HOME SCRAP",
      "pile": "38C",
      "operating_inventory_lbs": 972759,
      "month_begin_lbs": 987459,
      "receipts_lbs": 0,
      "issues_lbs": 0,
      "transfers_lbs": -14700,
      "adjustments_lbs": 0,
      "depletions_lbs": 0,
      "last_zero_date": "8/17/2021"
    },
    "38U": {
      "code": "10011669",
      "material": "439 HOME SCRAP",
      "pile": "38U",
      "operating_inventory_lbs": 50350,
      "month_begin_lbs": 4370,
      "receipts_lbs": 131780,
      "issues_lbs": 0,
      "transfers_lbs": -85800,
      "adjustments_lbs": 0,
      "depletions_lbs": 0,
      "last_zero_date": "11/11/2025"
    },
    "445": {
      "code": "10012170",
      "material": "55% CHRG CR LUMP EAF",
      "pile": "445",
      "operating_inventory_lbs": 182380,
      "month_begin_lbs": 798630,
      "receipts_lbs": 0,
      "issues_lbs": 0,
      "transfers_lbs": 0,
      "adjustments_lbs": 0,
      "depletions_lbs": 0,
      "last_zero_date": "12/8/2025"
    },
    "446": {
      "code": "10012170",
      "material": "55% CHRG CR LUMP EAF",
      "pile": "446",
      "operating_inventory_lbs": 3077550,
      "month_begin_lbs": 3246040,
      "receipts_lbs": 2838060,
      "issues_lbs": 0,
      "transfers_lbs": 0,
      "adjustments_lbs": 0,
      "depletions_lbs": 0,
      "last_zero_date": "12/2/2025"
    },
    "447": {
      "code": "10012170",
      "material": "55% CHRG CR LUMP EAF",
      "pile": "447",
      "operating_inventory_lbs": 1227830,
      "month_begin_lbs": 0,
      "receipts_lbs": 2510660,
      "issues_lbs": 0,
      "transfers_lbs": 0,
      "adjustments_lbs": 0,
      "depletions_lbs": 0,
      "last_zero_date": "2/3/2026"
    },
    "525": {
      "code": "10012284",
      "material": "EAF 75% FESI LUMP",
      "pile": "525",
      "operating_inventory_lbs": 364360,
      "month_begin_lbs": 422730,
      "receipts_lbs": 174920,
      "issues_lbs": 0,
      "transfers_lbs": 0,
      "adjustments_lbs": 0,
      "depletions_lbs": 0,
      "last_zero_date": "1/16/2024"
    },
    "923": {
      "code": "10012360",
      "material": "MOLYBDENUM OXIDE",
      "pile": "923",
      "operating_inventory_lbs": 30498,
      "month_begin_lbs": 57348,
      "receipts_lbs": 0,
      "issues_lbs": 0,
      "transfers_lbs": 0,
      "adjustments_lbs": 0,
      "depletions_lbs": 0,
      "last_zero_date": "12/22/2025"
    },
    "291": {
      "code": "10012420",
      "material": "CHARGE COKE",
      "pile": "291",
      "operating_inventory_lbs": 98556,
      "month_begin_lbs": 98556,
      "receipts_lbs": 0,
      "issues_lbs": 0,
      "transfers_lbs": 0,
      "adjustments_lbs": 0,
      "depletions_lbs": 0,
      "last_zero_date": "12/8/2017"
    },
    "29B": {
      "code": "10012420",
      "material": "CHARGE COKE",
      "pile": "29B",
      "operating_inventory_lbs": 74250,
      "month_begin_lbs": 74250,
      "receipts_lbs": 0,
      "issues_lbs": 0,
      "transfers_lbs": 0,
      "adjustments_lbs": 0,
      "depletions_lbs": 0,
      "last_zero_date": "6/27/2017"
    },
    "931": {
      "code": "10012998",
      "material": "MIXED ALLOYS",
      "pile": "931",
      "operating_inventory_lbs": 232595,
      "month_begin_lbs": 232595,
      "receipts_lbs": 0,
      "issues_lbs": 0,
      "transfers_lbs": 0,
      "adjustments_lbs": 0,
      "depletions_lbs": 0,
      "last_zero_date": "5/25/2016"
    },
    "984": {
      "code": "10031006",
      "material": "HI CALCIUM LIME EAF",
      "pile": "984",
      "operating_inventory_lbs": 52570,
      "month_begin_lbs": 110680,
      "receipts_lbs": 1335050,
      "issues_lbs": 0,
      "transfers_lbs": 0,
      "adjustments_lbs": 0,
      "depletions_lbs": 0,
      "last_zero_date": "11/14/2015"
    },
    "864": {
      "code": "10031008",
      "material": "DOLOMITIC LIME",
      "pile": "864",
      "operating_inventory_lbs": -334817,
      "month_begin_lbs": 135733,
      "receipts_lbs": 99500,
      "issues_lbs": 0,
      "transfers_lbs": 0,
      "adjustments_lbs": 0,
      "depletions_lbs": 0,
      "last_zero_date": "11/14/2015"
    }
  }

}
